beets_pitchfork-0.0.6-py3.6-nspkg.pth
beets_pitchfork-0.0.6.dist-info/METADATA
beets_pitchfork-0.0.6.dist-info/RECORD
beets_pitchfork-0.0.6.dist-info/WHEEL
beets_pitchfork-0.0.6.dist-info/namespace_packages.txt
beets_pitchfork-0.0.6.dist-info/top_level.txt
beetsplug/pitchfork.py
