Metadata-Version: 2.1
Name: beets-pitchfork
Version: 0.0.6
Summary: Pitchfork rating plugin for beets
Home-page: https://github.com/fortes/beets-pitchfork
Author: Filipe Fortes
Author-email: accounts@fortes.com
License: MIT
Platform: ALL
Classifier: License :: OSI Approved :: MIT License
Classifier: Programming Language :: Python :: 3
Classifier: Programming Language :: Python :: 3.6
Classifier: Operating System :: OS Independent
Classifier: Topic :: Multimedia :: Sound/Audio
Classifier: Topic :: Multimedia :: Sound/Audio :: Players :: MP3
Classifier: Environment :: Console
Requires-Dist: beets (>=1.4.7)
Requires-Dist: pitchfork (>=0.1.5)
